{
  "cars": [
    {
      "name": "雪佛兰科鲁兹",
      "imgSrc": "xfl.jpg",
      "detail": {
        "size": "三厢",
        "num": "1.6自动",
        "people": "乘坐5人"
      },
      "money": "137",
      "explain": ["hot", "new"]
    },
    {
      "name": "别克英朗",
      "imgSrc": "bk.jpg",
      "detail": {
        "size": "三厢",
        "num": "1.5自动",
        "people": "乘坐5人"
      },
      "money": "138",
      "explain": ["hot"]
    },
    {
      "name": "大众朗逸",
      "imgSrc": "dz.jpg",
      "detail": {
        "size": "三厢",
        "num": "1.6自动",
        "people": "乘坐5人"
      },
      "money": "149",
      "explain": ["hot", "new"]
    },
    {
      "name": "起亚K5",
      "imgSrc": "qy.jpg",
      "detail": {
        "size": "三厢",
        "num": "2.0自动",
        "people": "乘坐5人"
      },
      "money": "139",
      "explain": ["special"]
    }
  ]
}
